geomet_data_registry/__init__.py
geomet_data_registry/env.py
geomet_data_registry/log.py
geomet_data_registry/plugin.py
geomet_data_registry/util.py
geomet_data_registry/event/__init__.py
geomet_data_registry/event/file_.py
geomet_data_registry/event/message.py
geomet_data_registry/handler/__init__.py
geomet_data_registry/handler/base.py
geomet_data_registry/handler/core.py
geomet_data_registry/layer/__init__.py
geomet_data_registry/layer/base.py
geomet_data_registry/layer/cansips.py
geomet_data_registry/layer/cgsl.py
geomet_data_registry/layer/gdwps.py
geomet_data_registry/layer/geps.py
geomet_data_registry/layer/hrdpa.py
geomet_data_registry/layer/model_gem_global.py
geomet_data_registry/layer/model_gem_regional.py
geomet_data_registry/layer/model_giops.py
geomet_data_registry/layer/model_hrdps_continental.py
geomet_data_registry/layer/model_raqdps.py
geomet_data_registry/layer/model_raqdps_fw.py
geomet_data_registry/layer/model_raqdps_fw_ce.py
geomet_data_registry/layer/model_rdaqa_ce.py
geomet_data_registry/layer/model_riops.py
geomet_data_registry/layer/radar_1km.py
geomet_data_registry/layer/rdpa.py
geomet_data_registry/layer/rdwps.py
geomet_data_registry/layer/reps.py
geomet_data_registry/layer/wcps.py
geomet_data_registry/notifier/__init__.py
geomet_data_registry/notifier/base.py
geomet_data_registry/notifier/celery_.py
geomet_data_registry/store/__init__.py
geomet_data_registry/store/base.py
geomet_data_registry/store/redis_.py
geomet_data_registry/tileindex/__init__.py
geomet_data_registry/tileindex/base.py
geomet_data_registry/tileindex/elasticsearch_.py
tests/__init__.py
tests/test_util.py
geomet_data_registry-0.1.0.dist-info/LICENSE.md
geomet_data_registry-0.1.0.dist-info/METADATA
geomet_data_registry-0.1.0.dist-info/WHEEL
geomet_data_registry-0.1.0.dist-info/entry_points.txt
geomet_data_registry-0.1.0.dist-info/top_level.txt
geomet_data_registry-0.1.0.dist-info/RECORD
