Metadata-Version: 2.1
Name: geomet-data-registry
Version: 0.1.0
Summary: Geospatial Web Services for Canadian Weather data
Home-page: https://github.com/ECCC-MSC/geomet-data-registry
Author: Meteorological Service of Canada
Author-email: tom.kralidis@canada.ca
Maintainer: Meteorological Service of Canada
Maintainer-email: tom.kralidis@canada.ca
License: MIT
Keywords: geomet weather
Platform: all
Classifier: Development Status :: 4 - Beta
Classifier: Environment :: Console
Classifier: Intended Audience :: Developers
Classifier: Intended Audience :: Science/Research
Classifier: License :: OSI Approved :: GNU General Public License v3 (GPLv3)
Classifier: Operating System :: OS Independent
Classifier: Programming Language :: Python
License-File: LICENSE.md
Requires-Dist: click
Requires-Dist: elasticsearch
Requires-Dist: metpx-sarracenia
Requires-Dist: parse
Requires-Dist: python-dateutil
Requires-Dist: pyyaml
Requires-Dist: redis
